unifi_controller_api/__init__.py
unifi_controller_api/api_client.py
unifi_controller_api/device-models.json
unifi_controller_api/exceptions.py
unifi_controller_api/export.py
unifi_controller_api/logging.py
unifi_controller_api/utils.py
unifi_controller_api/models/__init__.py
unifi_controller_api/models/alarm.py
unifi_controller_api/models/client.py
unifi_controller_api/models/device.py
unifi_controller_api/models/event.py
unifi_controller_api/models/health.py
unifi_controller_api/models/networkconf.py
unifi_controller_api/models/portconf.py
unifi_controller_api/models/rogueap.py
unifi_controller_api/models/site.py
unifi_controller_api/models/wlanconf.py
unifi_controller_api-0.3.2.dist-info/licenses/LICENSE
unifi_controller_api-0.3.2.dist-info/METADATA
unifi_controller_api-0.3.2.dist-info/WHEEL
unifi_controller_api-0.3.2.dist-info/top_level.txt
unifi_controller_api-0.3.2.dist-info/RECORD
